LICENSE
setup.py
anemone/__init__.py
anemone/__main__.py
anemone_daisy_maker.egg-info/PKG-INFO
anemone_daisy_maker.egg-info/SOURCES.txt
anemone_daisy_maker.egg-info/dependency_links.txt
anemone_daisy_maker.egg-info/entry_points.txt
anemone_daisy_maker.egg-info/requires.txt
anemone_daisy_maker.egg-info/top_level.txt