Metadata-Version: 2.1
Name: anemone-daisy-maker
Version: 1.991
Summary: Create DAISY digital talking books from HTML text, MP3 audio and JSON time index data
Home-page: https://ssb22.user.srcf.net/indexer/anemone.html
Author: Silas S. Brown
Author-email: ssb22@cam.ac.uk
License: Apache 2
Platform: any
Classifier: Programming Language :: Python :: 3
Classifier: License :: OSI Approved :: Apache Software License
Classifier: Operating System :: OS Independent
Requires-Python: >=3.7
License-File: LICENSE
